README
setup.py
Moka.egg-info/PKG-INFO
Moka.egg-info/SOURCES.txt
Moka.egg-info/dependency_links.txt
Moka.egg-info/top_level.txt
moka/__init__.py
moka/speed.py