Metadata-Version: 1.0
Name: Moka
Version: 0.0.3
Summary: minimalist functional library
Home-page: https://github.com/phzbox/moka
Author: phzbOx
Author-email: phzbox@gmail.com
License: WTFPL
Keywords: functional
Platform: UNKNOWN
Classifier: Development Status :: 3 - Alpha
Classifier: Topic :: Utilities
